dd8/__init__.py
dd8/connectivity/__init__.py
dd8/connectivity/base.py
dd8/connectivity/binance_.py
dd8/connectivity/bit_.py
dd8/connectivity/bloomberg_.py
dd8/connectivity/coinbase_.py
dd8/connectivity/defillama_.py
dd8/connectivity/deribit_.py
dd8/connectivity/enums.py
dd8/connectivity/flipside_.py
dd8/connectivity/ftx_.py
dd8/connectivity/paradigm_.py
dd8/connectivity/talos_.py
dd8/data_science/__init__.py
dd8/data_science/cnn.py
dd8/data_science/data.py
dd8/data_science/enums.py
dd8/data_science/time_series.py
dd8/data_science/pytorch_/__init__.py
dd8/data_science/pytorch_/nlp.py
dd8/data_science/tensorflow_/__init__.py
dd8/finance/__init__.py
dd8/finance/algo.py
dd8/finance/base.py
dd8/finance/data.py
dd8/finance/enums.py
dd8/finance/meta_trader.py
dd8/finance/technical_analysis.py
dd8/finance/derivatives/__init__.py
dd8/finance/derivatives/rfq.py
dd8/finance/derivatives/vanilla/__init__.py
dd8/finance/derivatives/vanilla/base.py
dd8/finance/derivatives/vanilla/black_scholes.py
dd8/finance/derivatives/vanilla/enums.py
dd8/finance/derivatives/vanilla/instruments.py
dd8/finance/market_data/__init__.py
dd8/finance/market_data/base.py
dd8/finance/market_data/enums.py
dd8/finance/market_data/rates.py
dd8/finance/market_data/utils.py
dd8/finance/market_data/volatility.py
dd8/finance/spot/__init__.py
dd8/finance/spot/base.py
dd8/finance/spot/enums.py
dd8/finance/spot/instruments.py
dd8/utils/__init__.py
dd8/utils/chatbot.py
dd8/utils/dataframes.py
dd8/utils/distributed_.py
dd8/utils/fso.py
dd8/utils/logging_.py
dd8/utils/misc.py
dd8/utils/outlook_.py
dd8/utils/smtp_.py
dd8-0.0.24.dist-info/LICENSE
dd8-0.0.24.dist-info/METADATA
dd8-0.0.24.dist-info/WHEEL
dd8-0.0.24.dist-info/top_level.txt
dd8-0.0.24.dist-info/RECORD
