Metadata-Version: 2.1
Name: dd8
Version: 0.0.24
Summary: Package for Application of Data Science in Finance
Home-page: https://github.com/AiRiFiEd/dd8
Author: yqlim
Author-email: yuanqing87@gmail.com
License: MIT
License-File: LICENSE
Requires-Dist: python-telegram-bot
Requires-Dist: psutil
Requires-Dist: numpy
Requires-Dist: pandas
Requires-Dist: pytz
Requires-Dist: beautifulsoup4
Requires-Dist: requests
Requires-Dist: aiohttp
Requires-Dist: websockets
Requires-Dist: pika
